endpoints/__init__.py
endpoints/apps.py
endpoints/urls.py
endpoints/controllers/__init__.py
endpoints/controllers/base.py
endpoints/static/endpoints/css/bootstrap.min.css
endpoints/static/endpoints/css/wide-classes.css
endpoints/templates/endpoints/base.html
endpoints/templates/endpoints/endpoints.html
django_endpoints-0.0.3.dist-info/LICENSE
django_endpoints-0.0.3.dist-info/METADATA
django_endpoints-0.0.3.dist-info/WHEEL
django_endpoints-0.0.3.dist-info/top_level.txt
django_endpoints-0.0.3.dist-info/RECORD
