Metadata-Version: 2.1
Name: django-endpoints
Version: 0.0.3
Summary: Package to display all URLs of a Django application
Home-page: https://github.com/Artasov/django-endpoints
Author: xlartas
Author-email: ivanhvalevskey@gmail.com
Project-URL: Source, https://github.com/Artasov/django-endpoints
Project-URL: Tracker, https://github.com/Artasov/django-endpoints/issues
Keywords: django urls endpoints
Classifier: Framework :: Django
Classifier: Framework :: Django :: 4.0
Classifier: Programming Language :: Python :: 3.8
Classifier: Programming Language :: Python :: 3.9
Classifier: Programming Language :: Python :: 3.10
Classifier: Programming Language :: Python :: 3.11
Classifier: Programming Language :: Python :: 3.12
Classifier: Operating System :: OS Independent
Classifier: License :: OSI Approved :: MIT License
Classifier: Intended Audience :: Developers
Classifier: Topic :: Software Development :: Libraries :: Application Frameworks
Requires-Python: >=3.8
License-File: LICENSE
Requires-Dist: Django<5.3,>=4.0
